{
	"counter":	40,
	"templates":	["birb", "blobo", "grump", "feshHorizontal", "feshVertical"],
	"level":	{
		"levelEntries":	{
			"wave1":	{
				"waveKey":	"wave 30",
				"time":	180
			},
			"wave2":	{
				"waveKey":	"wave 37",
				"time":	180
			},
			"wave3":	{
				"waveKey":	"wave 38",
				"time":	180
			},
			"wave4":	{
				"waveKey":	"wave 39",
				"time":	180
			},
			"wave5":	{
				"waveKey":	"wave 40",
				"time":	180
			}
		},
		"playerChars":	{
		}
	},
	"waves":	{
		"wave 30":	{
			"waveEntries":	{
				"object1":	{
					"x":	382.933319,
					"y":	352,
					"element":	"BLUE",
					"aiKey":	"static",
					"templateKey":	"grump"
				}
			}
		},
		"wave 37":	{
			"waveEntries":	{
				"object1":	{
					"x":	382.933319,
					"y":	352,
					"element":	"BLUE",
					"aiKey":	"static",
					"templateKey":	"grump"
				}
			}
		},
		"wave 38":	{
			"waveEntries":	{
			}
		},
		"wave 39":	{
			"waveEntries":	{
			}
		},
		"wave 40":	{
			"waveEntries":	{
			}
		}
	}
}