{
	"levels":	{
		"level2":	{
			"levelEntries":	{
				"wave1":	{
					"waveKey":	"level2wave0",
					"time":	500
				}
			},
			"playerChars":	{
				"player1":	{
					"x":	500,
					"y":	200,
					"element":	"BLUE",
					"objectKey":	"playerChar1"
				},
				"player2":	{
					"x":	550,
					"y":	250,
					"element":	"GOLD",
					"objectKey":	"playerChar2"
				}
			}
		}
	},
	"waves":	{
		"level2wave0":	{
			"waveEntries":	{
				"object1":	{
					"aiKey":	"horizontal",
					"x":	0,
					"y":	100,
					"element":	"BLUE",
					"objectKey":	"object1",
					"zoneKeys":	["staticZoneBig"]
				},
				"object2":	{
					"aiKey":	"horizontal",
					"x":	940,
					"y":	440,
					"element":	"GOLD",
					"objectKey":	"object2",
					"zoneKeys":	["redBigCircleZone"]
				},
				"object3":	{
					"aiKey":	"vertical",
					"x":	0,
					"y":	100,
					"element":	"GOLD",
					"objectKey":	"object2",
					"zoneKeys":	["redBigCircleZone"]
				},
				"object4":	{
					"aiKey":	"vertical",
					"x":	940,
					"y":	440,
					"element":	"BLUE",
					"objectKey":	"object1",
					"zoneKeys":	["staticZoneBig"]
				},
				"object5":	{
					"aiKey":	"homing",
					"x":	178,
					"y":	181,
					"element":	"GOLD",
					"objectKey":	"object2"
				},
				"object6":	{
					"aiKey":	"homing",
					"x":	216,
					"y":	463,
					"element":	"GOLD",
					"objectKey":	"object2"
				},
				"object7":	{
					"aiKey":	"homing",
					"x":	36,
					"y":	75,
					"element":	"BLUE",
					"objectKey":	"object1"
				},
				"object8":	{
					"aiKey":	"homing",
					"x":	300,
					"y":	331,
					"element":	"GOLD",
					"objectKey":	"object2"
				},
				"object9":	{
					"aiKey":	"homing",
					"x":	640,
					"y":	425,
					"element":	"BLUE",
					"objectKey":	"object1"
				},
				"object10":	{
					"aiKey":	"homing",
					"x":	615,
					"y":	496,
					"element":	"GOLD",
					"objectKey":	"object2"
				}
			}
		}
	},
	"objects":	{
		    "circle": {
      "shapeKey": "circle",
      "animationKey": "whiteCircle"
    },
		"playerChar1":	{
			"shapeKey":	"shape1",
			"animationKey":	"blueCharAnimation"
		},
		"playerChar2":	{
			"shapeKey":	"shape1",
			"animationKey":	"redCharAnimation"
		},
		"object1":	{
			"shapeKey":	"shape1",
			"animationKey":	"blueEnemyAnimation"
		},
		"object2":	{
			"shapeKey":	"shape1",
			"animationKey":	"redEnemyAnimation"
		},
		    "big_circle": {
      "shapeKey": "big_circle",
      "animationKey": "whiteCircle"
    }
	},
	"shapes":	{    "circle": {
      "vertices": [
        0,
        -100,
        50.0,
        -86.6025403784,
        86.6025403784,
        -50.0,
        100,
        0,
        86.6025403784,
        50.0,
        50.0,
        86.6025403784,
        0,
        100,
        -50.0,
        86.6025403784,
        -86.6025403784,
        50.0,
        -100,
        0,
        -86.6025403784,
        -50.0,
        -50.0,
        -86.6025403784
      ]
    },
    "big_circle": {
      "vertices": [
        0,
        -200,
        100.0,
        -173.205080757,
        173.205080757,
        -100.0,
        200,
        0,
        173.205080757,
        100.0,
        100.0,
        173.205080757,
        0,
        200,
        -100.0,
        173.205080757,
        -173.205080757,
        100.0,
        -200,
        0,
        -173.205080757,
        -100.0,
        -100.0,
        -173.205080757
      ]
    },
		"shape1":	{
			"vertices":	[0, 0, 50, 0, 50, 50, 0, 50]
		}
	},
	"zones":	{
		    "staticZoneBig": {
      "type": "STATIC",
      "objectKey": "big_circle",
      "relX": 0,
      "relY": 0,
      "cooldown": 50,
      "duration": 50,
      "element": "BLUE"
    },
		"staticZone":	{
			"type":	"STATIC",
			"objectKey":	"circle",
			"relX":	0,
			"relY":	0,
			"cooldown":	50,
			"duration":	50,
			"element":	"BLUE"
		},
		"redBigCircleZone":	{
			"type":	"STATIC",
			"objectKey":	"big_circle",
			"relX":	0,
			"relY":	0,
			"cooldown":	0,
			"duration":	100,
			"element":	"GOLD"
		}
	}
}