{
    "MenuScreenData": {
        "menus": {
            "startMenu": {
                "menuKey": "startMenu",
                "menuBackgroundKey": "bg_dark_lake",
                "UIEntries": [
                    "openOptions",
                    "startGame",
                    "gameTitle",
                    "startMenuIcon"
                ]
            },
            "optionsMenu": {
                "menuKey": "optionsMenu",
                "UIEntries": [
                    "closeOptions",
                    "optionsTitle",
                    "volumeToggle"
                ]
            }
        }
    },
    "UIData": {
        "openOptions": {
            "type": "BUTTON",
            "buttonAction": {
                "type": "uiChange",
                "buttonTarget": "optionsMenu"
            },
            "buttonLabel": "Open Options",
            "x": 10,
            "y": 10,
            "width": 100,
            "height": 100
        },
        "startGame": {
            "type": "BUTTON",
            "buttonAction": {
                "type": "modeChange",
                "buttonTarget": "gameInit"
            },
            "buttonLabel": "Play Game",
            "x": 10,
            "y": 10,
            "width": 100,
            "height": 100
        },
        "gameTitle": {
            "type": "TEXT",
            "textValue": "Canon",
            "x": 20,
            "y": 20,
            "width": 100,
            "height": 100,
            "fontKey": "Charlemagne"
        },
        "startMenuIcon": {
            "type": "IMAGE",
            "x": 30,
            "y": 30,
            "width": 50,
            "height": 50,
            "textureKey": "bg_dark_lake"
        },
        "volumeIcon": {
            "type": "IMAGE",
            "x": 0,
            "y": 0,
            "width": 20,
            "height": 20,
            "textureKey": "volume_icon"
        },
        "closeOptions": {
            "type": "BUTTON",
            "buttonLabel": "Close Options",
            "buttonAction": {
                "type": "uiChange",
                "buttonTarget": "optionsMenu"
            },
            "x": 10,
            "y": 10,
            "width": 100,
            "height": 100
        },
        "volumeToggle": {
            "type": "BUTTON",
            "buttonLabel": "",
            "buttonContent": [
                "volumeIcon"
            ],
            "buttonAction": {
                "type": "fxTrigger",
                "fxKey": "volumeToggle"
            },
            "x": 100,
            "y": 100,
            "width": 40,
            "height": 40
        },
        "optionsTitle": {
            "type": "TEXT",
            "textValue": "Game Options",
            "x": 20,
            "y": 20,
            "width": 100,
            "height": 100,
            "fontKey": "Charlemagne"
        }
    }
}