{
    "name":	"separation",
    "counter":	10,
    "template names":	["birb", "blobo", "grump", "feshHorizontal", "feshVertical"],
    "levels":	{
        "separation":	{
            "key":	"separation",
            "levelEntries":	{
                "separation wave 06":	{
                    "key":	"separation wave 06",
                    "waveKey":	"separation wave 06",
                    "time":	360
                },
                "separation wave 07":	{
                    "key":	"separation wave 07",
                    "waveKey":	"separation wave 07",
                    "time":	480
                },
                "separation wave 10":	{
                    "key":	"separation wave 10",
                    "waveKey":	"separation wave 10",
                    "time":	360
                }
            },
            "playerChars":	{
                "player1":	{
                    "key":	"player1",
                    "x":	18.750000,
                    "y":	7.812500,
                    "element":	"GOLD",
                    "aiKey":	"",
                    "templateKey":	"playerCharMale"
                },
                "player2":	{
                    "key":	"player2",
                    "x":	12.500000,
                    "y":	7.812500,
                    "element":	"BLUE",
                    "aiKey":	"",
                    "templateKey":	"playerCharFemale"
                }
            }
        }
    },
    "waves":	{
        "separation wave 06":	{
            "key":	"separation wave 06",
            "waveEntries":	{
                "separation wave 06 object 1":	{
                    "key":	"separation wave 06 object 1",
                    "x":	25.666666,
                    "y":	7.100000,
                    "element":	"BLUE",
                    "aiKey":	"homing",
                    "templateKey":	"blobo"
                },
                "separation wave 06 object 2":	{
                    "key":	"separation wave 06 object 2",
                    "x":	25.666666,
                    "y":	9.566668,
                    "element":	"GOLD",
                    "aiKey":	"homing",
                    "templateKey":	"blobo"
                },
                "separation wave 06 object 3":	{
                    "key":	"separation wave 06 object 3",
                    "x":	5.966667,
                    "y":	9.933333,
                    "element":	"BLUE",
                    "aiKey":	"homing",
                    "templateKey":	"blobo"
                },
                "separation wave 06 object 4":	{
                    "key":	"separation wave 06 object 4",
                    "x":	6.033333,
                    "y":	7.400000,
                    "element":	"GOLD",
                    "aiKey":	"homing",
                    "templateKey":	"blobo"
                }
            }
        },
        "separation wave 07":	{
            "key":	"separation wave 07",
            "waveEntries":	{
                "separation wave 07 object 1":	{
                    "key":	"separation wave 07 object 1",
                    "x":	13.966666,
                    "y":	13.833333,
                    "element":	"GOLD",
                    "aiKey":	"homing",
                    "templateKey":	"blobo"
                },
                "separation wave 07 object 2":	{
                    "key":	"separation wave 07 object 2",
                    "x":	15.333333,
                    "y":	13.833333,
                    "element":	"BLUE",
                    "aiKey":	"homing",
                    "templateKey":	"blobo"
                },
                "separation wave 07 object 3":	{
                    "key":	"separation wave 07 object 3",
                    "x":	14,
                    "y":	3.733334,
                    "element":	"BLUE",
                    "aiKey":	"homing",
                    "templateKey":	"blobo"
                },
                "separation wave 07 object 4":	{
                    "key":	"separation wave 07 object 4",
                    "x":	15.433333,
                    "y":	3.733334,
                    "element":	"GOLD",
                    "aiKey":	"homing",
                    "templateKey":	"blobo"
                }
            }
        },
        "separation wave 10":	{
            "key":	"separation wave 10",
            "waveEntries":	{
                "separation wave 10 object 1":	{
                    "key":	"separation wave 10 object 1",
                    "x":	12.533334,
                    "y":	11,
                    "element":	"GOLD",
                    "aiKey":	"homing",
                    "templateKey":	"blobo"
                },
                "separation wave 10 object 2":	{
                    "key":	"separation wave 10 object 2",
                    "x":	16.833334,
                    "y":	11,
                    "element":	"BLUE",
                    "aiKey":	"homing",
                    "templateKey":	"blobo"
                },
                "separation wave 10 object 3":	{
                    "key":	"separation wave 10 object 3",
                    "x":	12.600000,
                    "y":	7.066667,
                    "element":	"BLUE",
                    "aiKey":	"homing",
                    "templateKey":	"blobo"
                },
                "separation wave 10 object 4":	{
                    "key":	"separation wave 10 object 4",
                    "x":	16.866667,
                    "y":	7,
                    "element":	"GOLD",
                    "aiKey":	"homing",
                    "templateKey":	"blobo"
                }
            }
        }
    }
}
